opensim_model_creator/Create_Model.py
opensim_model_creator/__init__.py
opensim_model_creator/Functions/_init_.py
opensim_model_creator/Functions/bone_utils.py
opensim_model_creator/Functions/file_utils.py
opensim_model_creator/Functions/general_utils.py
opensim_model_creator/Functions/muscle_utils.py
opensim_model_creator/High_Level_Inputs/Feet.osim
opensim_model_creator/High_Level_Inputs/Feet_raja.osim
opensim_model_creator/High_Level_Inputs/ScaleSettings.xml
opensim_model_creator/High_Level_Inputs/ScaleSettings_old.xml
opensim_model_creator/High_Level_Inputs/l_bofoot.vtp
opensim_model_creator/High_Level_Inputs/l_foot.vtp
opensim_model_creator/High_Level_Inputs/l_talus.vtp
opensim_model_creator/High_Level_Inputs/opensim.log
opensim_model_creator/High_Level_Inputs/r_bofoot.vtp
opensim_model_creator/High_Level_Inputs/r_foot.vtp
opensim_model_creator/High_Level_Inputs/r_talus.vtp
opensim_model_creator/High_Level_Inputs/final_node_numbers/Femur/105_NodeNo.txt
opensim_model_creator/High_Level_Inputs/final_node_numbers/Femur/106_NodeNo.txt
opensim_model_creator/High_Level_Inputs/final_node_numbers/Femur/107_NodeNo.txt
opensim_model_creator/High_Level_Inputs/final_node_numbers/Femur/108_NodeNo.txt
opensim_model_creator/High_Level_Inputs/final_node_numbers/Femur/110_NodeNo.txt
opensim_model_creator/High_Level_Inputs/final_node_numbers/Femur/111_112_113_NodeNo.txt
opensim_model_creator/High_Level_Inputs/final_node_numbers/Femur/114_NodeNo.txt
opensim_model_creator/High_Level_Inputs/final_node_numbers/Femur/116b_NodeNo.txt
opensim_model_creator/High_Level_Inputs/final_node_numbers/Femur/116c_NodeNo.txt
opensim_model_creator/High_Level_Inputs/final_node_numbers/Femur/116d_NodeNo.txt
opensim_model_creator/High_Level_Inputs/final_node_numbers/Femur/117_NodeNo.txt
opensim_model_creator/High_Level_Inputs/final_node_numbers/Femur/118_NodeNo.txt
opensim_model_creator/High_Level_Inputs/final_node_numbers/Femur/119_NodeNo.txt
opensim_model_creator-0.1.18.dist-info/METADATA
opensim_model_creator-0.1.18.dist-info/WHEEL
opensim_model_creator-0.1.18.dist-info/top_level.txt
opensim_model_creator-0.1.18.dist-info/RECORD
